LICENSE.txt
MANIFEST.in
README.txt
dbgpClient.py
setup.py
bin/pydbgp
bin/pydbgpproxy
dbgp/__init__.py
dbgp/_pyclient.py
dbgp/client.py
dbgp/common.py
dbgp/listcmd.py
dbgp/server.py
dbgp/serverBase.py
komodo_python_dbgp.egg-info/PKG-INFO
komodo_python_dbgp.egg-info/SOURCES.txt
komodo_python_dbgp.egg-info/dependency_links.txt
komodo_python_dbgp.egg-info/not-zip-safe
komodo_python_dbgp.egg-info/top_level.txt
libs/linux-x86/_client24.so
libs/linux-x86/_client25.so
libs/linux-x86/_client26.so
libs/linux-x86/_client27.so
libs/linux-x86_64/_client24.so
libs/linux-x86_64/_client25.so
libs/linux-x86_64/_client26.so
libs/linux-x86_64/_client27.so
libs/win32-x86/_client24.pyd
libs/win32-x86/_client25.pyd
libs/win32-x86/_client26.pyd
libs/win32-x86/_client27.pyd