Metadata-Version: 1.1
Name: komodo-python-dbgp
Version: 11.0
Summary: The ActiveState Komodo DBGP server
Home-page: http://github.com/agroszer/komodo-python-dbgp
Author: Adam Groszer
Author-email: agroszer@gmail.com
License: UNKNOWN
Platform: UNKNOWN
Classifier: Development Status :: 5 - Production/Stable
Classifier: Intended Audience :: Developers
Classifier: Programming Language :: Python
Classifier: Programming Language :: Python :: 2
Classifier: Programming Language :: Python :: 2.4
Classifier: Programming Language :: Python :: 2.5
Classifier: Programming Language :: Python :: 2.6
Classifier: Programming Language :: Python :: 2.7
Classifier: Programming Language :: Python :: Implementation :: CPython
